MANIFEST.in
Makefile
README
setup.py
test/__init__.py
test/__init__.pyc
test/test_compile.py
test/test_write_store.py
test/__pycache__/test_compile.cpython-27-PYTEST.pyc
test/__pycache__/test_write_store.cpython-27-PYTEST.pyc
tiddlywebplugins/__init__.py
tiddlywebplugins/pkgstore.py
tiddlywebplugins.pkgstore.egg-info/PKG-INFO
tiddlywebplugins.pkgstore.egg-info/SOURCES.txt
tiddlywebplugins.pkgstore.egg-info/dependency_links.txt
tiddlywebplugins.pkgstore.egg-info/namespace_packages.txt
tiddlywebplugins.pkgstore.egg-info/not-zip-safe
tiddlywebplugins.pkgstore.egg-info/requires.txt
tiddlywebplugins.pkgstore.egg-info/top_level.txt