Metadata-Version: 1.0
Name: tiddlywebplugins.pkgstore
Version: 0.3
Summary: Store TiddlyWeb entities in Python package resources
Home-page: http://pypi.python.org/pypi/tiddlywebplugins.pkgstore
Author: Chris Dent
Author-email: cdent@peermore.com
License: UNKNOWN
Platform: Posix; MacOS X; Windows
